<?xml version="1.0" encoding="UTF-8" ?>
<!DOCTYPE mapper PUBLIC "-//mybatis.org//DTD Mapper 3.0//EN" "http://mybatis.org/dtd/mybatis-3-mapper.dtd" >
<mapper namespace="com.xd.mapper.SyCosttypeMapper" >
  <resultMap id="BaseResultMap" type="com.xd.entity.SyCosttype" >
    <!--
      WARNING - @mbggenerated
      This element is automatically generated by MyBatis Generator, do not modify.
    -->
    <id column="ID" property="id" jdbcType="INTEGER" />
    <result column="Kind" property="kind" jdbcType="INTEGER" />
    <result column="Code" property="code" jdbcType="VARCHAR" />
    <result column="CostTypeName" property="costtypename" jdbcType="VARCHAR" />
    <result column="FullName" property="fullname" jdbcType="VARCHAR" />
    <result column="Price" property="price" jdbcType="DECIMAL" />
    <result column="SurchargeText" property="surchargetext" jdbcType="VARCHAR" />
    <result column="Remark" property="remark" jdbcType="VARCHAR" />
    <result column="Disabled" property="disabled" jdbcType="BIT" />
  </resultMap>
  <sql id="Base_Column_List" >
    <!--
      WARNING - @mbggenerated
      This element is automatically generated by MyBatis Generator, do not modify.
    -->
    ID, Kind, Code, CostTypeName, FullName, Price, SurchargeText, Remark, Disabled
  </sql>

  <select id="selectByPrimaryKey" resultMap="BaseResultMap" parameterType="java.lang.Integer" >
    <!--
      WARNING - @mbggenerated
      This element is automatically generated by MyBatis Generator, do not modify.
    -->
    select 
    <include refid="Base_Column_List" />
    from sy_costtype
    where ID = #{id,jdbcType=INTEGER}
  </select>

  <delete id="deleteByPrimaryKey" parameterType="java.lang.Integer" >
    <!--
      WARNING - @mbggenerated
      This element is automatically generated by MyBatis Generator, do not modify.
    -->
    delete from sy_costtype
    where ID = #{id,jdbcType=INTEGER}
  </delete>

  <insert id="insert" parameterType="com.xd.entity.SyCosttype" >
    <!--
      WARNING - @mbggenerated
      This element is automatically generated by MyBatis Generator, do not modify.
    -->
    insert into sy_costtype (ID, Kind, Code, 
      CostTypeName, FullName, Price, 
      SurchargeText, Remark, Disabled
      )
    values (#{id,jdbcType=INTEGER}, #{kind,jdbcType=INTEGER}, #{code,jdbcType=VARCHAR}, 
      #{costtypename,jdbcType=VARCHAR}, #{fullname,jdbcType=VARCHAR}, #{price,jdbcType=DECIMAL}, 
      #{surchargetext,jdbcType=VARCHAR}, #{remark,jdbcType=VARCHAR}, #{disabled,jdbcType=BIT}
      )
  </insert>
  <insert id="insertSelective" parameterType="com.xd.entity.SyCosttype" >
    <!--
      WARNING - @mbggenerated
      This element is automatically generated by MyBatis Generator, do not modify.
    -->
    insert into sy_costtype
    <trim prefix="(" suffix=")" suffixOverrides="," >
      <if test="id != null" >
        ID,
      </if>
      <if test="kind != null" >
        Kind,
      </if>
      <if test="code != null" >
        Code,
      </if>
      <if test="costtypename != null" >
        CostTypeName,
      </if>
      <if test="fullname != null" >
        FullName,
      </if>
      <if test="price != null" >
        Price,
      </if>
      <if test="surchargetext != null" >
        SurchargeText,
      </if>
      <if test="remark != null" >
        Remark,
      </if>
      <if test="disabled != null" >
        Disabled,
      </if>
    </trim>
    <trim prefix="values (" suffix=")" suffixOverrides="," >
      <if test="id != null" >
        #{id,jdbcType=INTEGER},
      </if>
      <if test="kind != null" >
        #{kind,jdbcType=INTEGER},
      </if>
      <if test="code != null" >
        #{code,jdbcType=VARCHAR},
      </if>
      <if test="costtypename != null" >
        #{costtypename,jdbcType=VARCHAR},
      </if>
      <if test="fullname != null" >
        #{fullname,jdbcType=VARCHAR},
      </if>
      <if test="price != null" >
        #{price,jdbcType=DECIMAL},
      </if>
      <if test="surchargetext != null" >
        #{surchargetext,jdbcType=VARCHAR},
      </if>
      <if test="remark != null" >
        #{remark,jdbcType=VARCHAR},
      </if>
      <if test="disabled != null" >
        #{disabled,jdbcType=BIT},
      </if>
    </trim>
  </insert>
  <update id="updateByPrimaryKeySelective" parameterType="com.xd.entity.SyCosttype" >
    <!--
      WARNING - @mbggenerated
      This element is automatically generated by MyBatis Generator, do not modify.
    -->
    update sy_costtype
    <set >
      <if test="kind != null" >
        Kind = #{kind,jdbcType=INTEGER},
      </if>
      <if test="code != null" >
        Code = #{code,jdbcType=VARCHAR},
      </if>
      <if test="costtypename != null" >
        CostTypeName = #{costtypename,jdbcType=VARCHAR},
      </if>
      <if test="fullname != null" >
        FullName = #{fullname,jdbcType=VARCHAR},
      </if>
      <if test="price != null" >
        Price = #{price,jdbcType=DECIMAL},
      </if>
      <if test="surchargetext != null" >
        SurchargeText = #{surchargetext,jdbcType=VARCHAR},
      </if>
      <if test="remark != null" >
        Remark = #{remark,jdbcType=VARCHAR},
      </if>
      <if test="disabled != null" >
        Disabled = #{disabled,jdbcType=BIT},
      </if>
    </set>
    where ID = #{id,jdbcType=INTEGER}
  </update>
  <update id="updateByPrimaryKey" parameterType="com.xd.entity.SyCosttype" >
    <!--
      WARNING - @mbggenerated
      This element is automatically generated by MyBatis Generator, do not modify.
    -->
    update sy_costtype
    set Kind = #{kind,jdbcType=INTEGER},
      Code = #{code,jdbcType=VARCHAR},
      CostTypeName = #{costtypename,jdbcType=VARCHAR},
      FullName = #{fullname,jdbcType=VARCHAR},
      Price = #{price,jdbcType=DECIMAL},
      SurchargeText = #{surchargetext,jdbcType=VARCHAR},
      Remark = #{remark,jdbcType=VARCHAR},
      Disabled = #{disabled,jdbcType=BIT}
    where ID = #{id,jdbcType=INTEGER}
  </update>
</mapper>